[
  {
    "py/object": "model.contact.Contact",
    "firstname": "firstnameER",
    "lastname": "lastnameKhZYlD5apqBDGoH",
    "address": "addressvQeA",
    "homephone": "homeks",
    "mobilephone": "mobile1Z19TSB",
    "workphone": "addressopZ9xfcrbn",
    "secondaryphone": "secondaryphone",
    "first_email": "emailxgjc",
    "second_email": "email2SKNIOWXykKbq4d77KNd59SQOhBYNm",
    "third_email": "email3p4mnscuEqCHushB9BJt5aNBD",
    "all_phones_from_home_page": null,
    "all_emails_from_home_page": null,
    "id": null
  },
  {
    "py/object": "model.contact.Contact",
    "firstname": "firstnamerpGKCi",
    "lastname": "lastnamenSHFejpr6JcuT",
    "address": "addressIo8kO4oQvFAiAi",
    "homephone": "homeYXU",
    "mobilephone": "mobileYV4AQZ",
    "workphone": "addresshN1o8ADHpEc",
    "secondaryphone": "secondaryphone",
    "first_email": "emailXUbp0n48f",
    "second_email": "email26udKCnl04cqcmiobz6P9k9t5nvFPIuaLp8cyMi",
    "third_email": "email3Vfg5WSWvzXWFM5fJfIW8wU2cb133g4QKOknK",
    "all_phones_from_home_page": null,
    "all_emails_from_home_page": null,
    "id": null
  },
  {
    "py/object": "model.contact.Contact",
    "firstname": "firstnameP",
    "lastname": "lastnamezvzv3QB6",
    "address": "address1Rqofoflk0Xu",
    "homephone": "homeOoTyvI",
    "mobilephone": "mobileqZU",
    "workphone": "address",
    "secondaryphone": "secondaryphoneh15Gpt",
    "first_email": "emailpW",
    "second_email": "email2IY7L5HOPFmuSacLowOPu5UPBEeGYrQcwSaA",
    "third_email": "email30X",
    "all_phones_from_home_page": null,
    "all_emails_from_home_page": null,
    "id": null
  },
  {
    "py/object": "model.contact.Contact",
    "firstname": "firstnameCZ2Xi",
    "lastname": "lastnameVvtRry8xLFq8XFS8G",
    "address": "address84kfZZPSBSXo3TYRX",
    "homephone": "homewC",
    "mobilephone": "mobiledsgI",
    "workphone": "addressICE3EEpWiBFwaxqU",
    "secondaryphone": "secondaryphoneaizuBui",
    "first_email": "email6NOKvc1T",
    "second_email": "email2SnanJmjIHotBN7w7ozIF35QvI1mh",
    "third_email": "email3axykB219qCZ3sxruhgRu1SAqDB6",
    "all_phones_from_home_page": null,
    "all_emails_from_home_page": null,
    "id": null
  },
  {
    "py/object": "model.contact.Contact",
    "firstname": "firstnameCT",
    "lastname": "lastnamee0WJBcrf2",
    "address": "addressrWsOgEfgatrt5FQJCos",
    "homephone": "homeI",
    "mobilephone": "mobileEVi",
    "workphone": "addresseduUk9K3KjwjdJ",
    "secondaryphone": "secondaryphoneVlYw",
    "first_email": "email",
    "second_email": "email2wzB0aQvydAlJbIXBU",
    "third_email": "email3MvzBzOAWNyz3QKVvuT1g9UvvKQ9UUYIL",
    "all_phones_from_home_page": null,
    "all_emails_from_home_page": null,
    "id": null
  }
]